shopcube/.test.prod.env
shopcube/__init__.py
shopcube/__main__.py
shopcube/app.py
shopcube/config.json
shopcube/config.py
shopcube/config_demo.json
shopcube/conftest.py
shopcube/init.py
shopcube/manage.py
shopcube/shopyo_admin.py
shopcube/wsgi.py
shopcube/migrations/README
shopcube/migrations/alembic.ini
shopcube/migrations/env.py
shopcube/migrations/script.py.mako
shopcube/migrations/versions/91729da996fd_.py
shopcube/modules/__init__.py
shopcube/modules/box__default/box_info.json
shopcube/modules/box__default/appadmin/__init__.py
shopcube/modules/box__default/appadmin/admin.py
shopcube/modules/box__default/appadmin/info.json
shopcube/modules/box__default/appadmin/models.py
shopcube/modules/box__default/appadmin/view.py
shopcube/modules/box__default/appadmin/static/icon.svg
shopcube/modules/box__default/appadmin/templates/appadmin/add.html
shopcube/modules/box__default/appadmin/templates/appadmin/edit.html
shopcube/modules/box__default/appadmin/templates/appadmin/index.html
shopcube/modules/box__default/appadmin/templates/appadmin/roles.html
shopcube/modules/box__default/appadmin/templates/appadmin/blocks/sidebar.html
shopcube/modules/box__default/appadmin/tests/test_admin.py
shopcube/modules/box__default/appadmin/tests/test_models.py
shopcube/modules/box__default/auth/decorators.py
shopcube/modules/box__default/auth/forms.py
shopcube/modules/box__default/auth/info.json
shopcube/modules/box__default/auth/models.py
shopcube/modules/box__default/auth/upload.py
shopcube/modules/box__default/auth/view.py
shopcube/modules/box__default/auth/static/style.css
shopcube/modules/box__default/auth/templates/auth/login.html
shopcube/modules/box__default/auth/templates/auth/register.html
shopcube/modules/box__default/auth/templates/auth/shop_login.html
shopcube/modules/box__default/auth/templates/auth/unconfirmed.html
shopcube/modules/box__default/auth/templates/auth/blocks/login_form.html
shopcube/modules/box__default/auth/templates/auth/blocks/register_form.html
shopcube-5.0.0.dist-info/licenses/LICENSE
shopcube-5.0.0.dist-info/METADATA
shopcube-5.0.0.dist-info/WHEEL
shopcube-5.0.0.dist-info/entry_points.txt
shopcube-5.0.0.dist-info/top_level.txt
shopcube-5.0.0.dist-info/RECORD
