Metadata-Version: 2.4
Name: shopcube
Version: 5.0.0
Summary: E-commerce solution
Author-email: Abdur-Rahmaan Janhangeer & contributors <arj.python@gmail.com>
License: MIT
Project-URL: Bug Reports, https://github.com/Abdur-RahmaanJ/shopcube/issues
Project-URL: Source, https://github.com/Abdur-RahmaanJ/shopcube/
Keywords: flask,pos,management,shop,ecommerce,cms,erp,e-commerce
Classifier: Development Status :: 4 - Beta
Classifier: Intended Audience :: Developers
Classifier: License :: OSI Approved :: MIT License
Classifier: Programming Language :: Python :: 3.7
Classifier: Programming Language :: Python :: 3.8
Classifier: Programming Language :: Python :: 3.9
Classifier: Programming Language :: Python :: 3.10
Classifier: Programming Language :: Python :: 3.11
Classifier: Programming Language :: Python :: 3.12
Classifier: Programming Language :: Python :: 3.13
License-File: LICENSE
Requires-Dist: alembic==1.7.3
Requires-Dist: click==8.0.1
Requires-Dist: dnspython==2.1.0
Requires-Dist: email-validator==1.1.3
Requires-Dist: et-xmlfile==1.1.0
Requires-Dist: flask==2.2.0
Requires-Dist: flask-admin==1.6.0
Requires-Dist: flask-login==0.6.2
Requires-Dist: flask-mailman==0.3.0
Requires-Dist: flask-marshmallow==1.0.0
Requires-Dist: flask-migrate==3.1.0
Requires-Dist: flask-reuploaded==1.2.0
Requires-Dist: flask-sqlalchemy==2.5.1
Requires-Dist: flask-wtf==1.0.0
Requires-Dist: greenlet==3.1.1
Requires-Dist: idna==2.10
Requires-Dist: itsdangerous==2.0.1
Requires-Dist: jinja2==3.0.1
Requires-Dist: mako==1.1.5
Requires-Dist: markupsafe==2.1.1
Requires-Dist: marshmallow==3.14.1
Requires-Dist: marshmallow-sqlalchemy==0.26.1
Requires-Dist: mkdocs-material-extensions==1.0.3
Requires-Dist: numpy==2.1.1
Requires-Dist: openpyxl==3.0.10
Requires-Dist: packaging==24.1
Requires-Dist: pandas==2.2.2
Requires-Dist: pillow==10.4.0
Requires-Dist: pymysql==1.0.2
Requires-Dist: python-dateutil==2.8.2
Requires-Dist: pytz==2022.2.1
Requires-Dist: shopyo==4.13.1
Requires-Dist: six==1.16.0
Requires-Dist: sqlalchemy==1.4.46
Requires-Dist: tzdata==2024.1
Requires-Dist: werkzeug==2.2.2
Requires-Dist: wtforms==3.0.1
Requires-Dist: setuptools
Dynamic: license-file
